apparent/.DS_Store
apparent/__init__.py
apparent/reports.py
apparent/timing.py
apparent-0.1.4.dist-info/LICENSE.txt
apparent-0.1.4.dist-info/WHEEL
apparent-0.1.4.dist-info/METADATA
apparent-0.1.4.dist-info/RECORD
