Metadata-Version: 2.1
Name: apparent
Version: 0.1.4
Summary: A toolkit for code observability in-process data collection: timing, counters, and metrics.
Keywords: apparent,observability,monitoring,timers,timing,counters,metrics
Author-email: Arnon Moscona <arnon@moscona.com>
Maintainer-email: Arnon Moscona <arnon@moscona.com>
Requires-Python: >=3.9
Classifier: Development Status :: 4 - Beta
Classifier: Programming Language :: Python
Classifier: License :: OSI Approved :: Apache Software License
Requires-Dist: pdoc ; extra == "dev"
Requires-Dist: coverage ; extra == "test"
Project-URL: repository, https://github.com/arnonmoscona/apparent
Provides-Extra: dev
Provides-Extra: test
